fineocr/__init__.py
fineocr/__main__.py
fineocr/doc.py
fineocr/finescanner.py
fineocr/spinner.py
fineocr/urlreader.py
fineocr-0.3.dist-info/METADATA
fineocr-0.3.dist-info/WHEEL
fineocr-0.3.dist-info/entry_points.txt
fineocr-0.3.dist-info/top_level.txt
fineocr-0.3.dist-info/RECORD
