Metadata-Version: 2.1
Name: fineocr
Version: 0.3
Summary: FineScanner Mobile OCR for free
Home-page: https://github.com/kfur/fineocr
Author: kfur
Author-email: deniskovpen@gmail.com
License: UNKNOWN
Download-URL: https://github.com/kfur/fineocr/archive/refs/tags/v0.3.tar.gz
Keywords: OCR
Platform: UNKNOWN
Classifier: Development Status :: 4 - Beta
Classifier: License :: OSI Approved :: GNU Affero General Public License v3 or later (AGPLv3+)
Classifier: Framework :: AsyncIO
Classifier: Programming Language :: Python
Classifier: Programming Language :: Python :: 3
Classifier: Programming Language :: Python :: 3.7
Classifier: Programming Language :: Python :: 3.8
Requires-Python: ~=3.7
Requires-Dist: aiohttp (>=3.6)
Requires-Dist: aiofiles (>=0.5)
